suzaku/.DS_Store
suzaku/__init__.py
suzaku/__main__.py
suzaku/base/__init__.py
suzaku/base/appbase.py
suzaku/base/windowbase.py
suzaku/const.py
suzaku/event.py
suzaku/misc.py
suzaku/resources/imgs/.DS_Store
suzaku/resources/imgs/icon.ico
suzaku/resources/themes/dark.json
suzaku/resources/themes/light.json
suzaku/resources/themes/sv_1light.json
suzaku/resources/themes/sv_2dark.json
suzaku/styles/__init__.py
suzaku/styles/color.py
suzaku/styles/drop_shadow.py
suzaku/styles/font.py
suzaku/styles/point.py
suzaku/styles/texture.py
suzaku/styles/theme.py
suzaku/var.py
suzaku/widgets/__init__.py
suzaku/widgets/app.py
suzaku/widgets/appwindow.py
suzaku/widgets/button.py
suzaku/widgets/canvas.py
suzaku/widgets/card.py
suzaku/widgets/checkbox.py
suzaku/widgets/checkitem.py
suzaku/widgets/combobox.py
suzaku/widgets/container.py
suzaku/widgets/draw.py
suzaku/widgets/empty.py
suzaku/widgets/entry.py
suzaku/widgets/filedialog.py
suzaku/widgets/frame.py
suzaku/widgets/hynix.py
suzaku/widgets/image.py
suzaku/widgets/label.py
suzaku/widgets/lineinput.py
suzaku/widgets/listbox.py
suzaku/widgets/listitem.py
suzaku/widgets/menu.py
suzaku/widgets/menubar.py
suzaku/widgets/menuitem.py
suzaku/widgets/messagebox.py
suzaku/widgets/mutiline_input.py
suzaku/widgets/popup.py
suzaku/widgets/popupmenu.py
suzaku/widgets/popupwindow.py
suzaku/widgets/progressbar.py
suzaku/widgets/radiobox.py
suzaku/widgets/radioitem.py
suzaku/widgets/separator.py
suzaku/widgets/sizegrip.py
suzaku/widgets/slider.py
suzaku/widgets/stack.py
suzaku/widgets/switch.py
suzaku/widgets/switchbox.py
suzaku/widgets/tabbar.py
suzaku/widgets/tabbutton.py
suzaku/widgets/table.py
suzaku/widgets/tabs.py
suzaku/widgets/text.py
suzaku/widgets/textbutton.py
suzaku/widgets/tipbar.py
suzaku/widgets/titlebar.py
suzaku/widgets/tooltip.py
suzaku/widgets/treeview.py
suzaku/widgets/widget.py
suzaku/widgets/window.py
suzaku-0.2.1.dist-info/METADATA
suzaku-0.2.1.dist-info/WHEEL
suzaku-0.2.1.dist-info/RECORD
