Metadata-Version: 2.4
Name: suzaku
Version: 0.2.1
Summary: Yet another GUI lib, looks and performs better than tkinter.
License-Expression: MIT
Keywords: suzaku,future,lightweight,gui,framework
Author: XiangQinxi
Author-email: XiangQinxi@outlook.com
Requires-Python: >=3.11
Classifier: Programming Language :: Python :: 3
Classifier: Programming Language :: Python :: 3.11
Classifier: Programming Language :: Python :: 3.12
Classifier: Programming Language :: Python :: 3.13
Classifier: Programming Language :: Python :: 3.14
Requires-Dist: glfw
Requires-Dist: pyopengl
Requires-Dist: skia-python
